know/__init__.py
know/audio_to_store.py
know-0.0.3.dist-info/LICENSE
know-0.0.3.dist-info/METADATA
know-0.0.3.dist-info/WHEEL
know-0.0.3.dist-info/top_level.txt
know-0.0.3.dist-info/RECORD
