Metadata-Version: 2.1
Name: know
Version: 0.0.3
Summary: Funnel live streams of data into storage and other processes
Home-page: https://github.com/otosense/know
Author: OtoSense
License: apache-2.0
Platform: any
Requires-Dist: atypes
Requires-Dist: dol
Requires-Dist: recode
Requires-Dist: stream2py
Requires-Dist: taped
